{
  "date": "2026-02-18",
  "day_trades": 1,
  "day_wins": 0,
  "day_losses": 1,
  "day_pnl": -8.0,
  "cumulative_trades": 36,
  "cumulative_wins": 33,
  "cumulative_losses": 3,
  "cumulative_win_rate": "91.7%",
  "cumulative_pnl": 13952.5,
  "details": [
    {
      "ticker": "SOXS",
      "strategy": "SHORT",
      "entry_date": "2026-02-10",
      "entry_price": 35.8,
      "exit_price": 35.6,
      "shares": 40,
      "pnl_pct": -0.56,
      "pnl_dollar": -8.0,
      "reason": "EXPIRED"
    }
  ]
}